latex/__init__.py
latex/__main__.py
latex/commands/__init__.py
latex/commands/build.py
latex/commands/init.py
latex/services/__init__.py
latex/services/logging.py
latex/services/paths.py
latex/templates/__init__.py
latex_jinja-0.3.1.dist-info/METADATA
latex_jinja-0.3.1.dist-info/WHEEL
latex_jinja-0.3.1.dist-info/licenses/LICENSE.md
latex_jinja-0.3.1.dist-info/RECORD
