Metadata-Version: 2.3
Name: latex-jinja
Version: 0.3.1
Summary: Latex templating with Jinja and PDF conversion.
Project-URL: repository, https://github.com/JoelLefkowitz/latex
Project-URL: homepage, https://joellefkowitz.github.io/latex
Author-email: Joel Lefkowitz <joellefkowitz@hotmail.com>
License: # MIT License
Keywords: PDF,jinja,latex,template
Classifier: License :: OSI Approved :: MIT License
Classifier: Programming Language :: Python :: 3.8
Classifier: Programming Language :: Python :: 3.9
Classifier: Programming Language :: Python :: 3.10
Classifier: Programming Language :: Python :: 3.11
Requires-Python: >=3.8
Requires-Dist: docopt~=0.6.2
Requires-Dist: jinja2~=3.0.0
Requires-Dist: rich~=13.9.4
Provides-Extra: all
Requires-Dist: autoflake~=1.4; extra == 'all'
Requires-Dist: black~=22.3.0; extra == 'all'
Requires-Dist: build~=1.2.0; extra == 'all'
Requires-Dist: bump2version~=1.0.0; extra == 'all'
Requires-Dist: furo~=2024.1.0; extra == 'all'
Requires-Dist: isort~=5.10.0; extra == 'all'
Requires-Dist: matplotlib~=3.8.0; extra == 'all'
Requires-Dist: mypy~=0.9; extra == 'all'
Requires-Dist: myst-parser~=2.0.0; extra == 'all'
Requires-Dist: pylint~=2.17.0; extra == 'all'
Requires-Dist: pytest-cov~=5.0.0; extra == 'all'
Requires-Dist: pytest~=7.1.0; extra == 'all'
Requires-Dist: sphinx-autoapi~=3.0.0; extra == 'all'
Requires-Dist: sphinxext-opengraph~=0.9.0; extra == 'all'
Requires-Dist: sphinx~=7.2.0; extra == 'all'
Requires-Dist: thx~=0.5.0; extra == 'all'
Requires-Dist: trufflehog3~=3.0.0; extra == 'all'
Requires-Dist: twine~=5.0.0; extra == 'all'
Requires-Dist: walkmate~=1.5.0; extra == 'all'
